{
    "CONTACT_SERVICE_URL": "http://stg.eum.unicefuganda.org/contacts/",
    "BACKEND_URLS": {
        "DISTRIBUTION_REPORT": "/api/distribution-report/",
        "DISTRIBUTION_PLAN": "/api/distribution-plan/",
        "DISTRIBUTION_PLAN_NODE": "/api/distribution-plan-node/",
        "ITEM": "/api/item/",
        "ITEM_UNIT": "/api/item-unit/",
        "CONSIGNEE": "/api/consignee/",
        "DISTRIBUTION_PLAN_LINE_ITEM": "/api/distribution-plan-line-item/",
        "SALES_ORDER": "/api/sales-order/",
        "SALES_ORDER_ITEM": "/api/sales-order-item/",
        "PURCHASE_ORDER": "/api/purchase-order/",
        "PURCHASE_ORDER_ITEM": "/api/purchase-order-item/",
        "CONSIGNEE_PURCHASE_ORDERS": "/api/consignee-purchase-orders/",
        "STOCK_REPORT": "/api/stock-report/",
        "DISTRIBUTION_PLAN_RESPONSES": "/api/distribution-plan-responses/",
        "PROGRAMME": "/api/programme/",
        "USER": "/api/user/",
        "IMPORT_SALES_ORDERS": "/api/import-sales-orders/",
        "PERMISSION": "/api/permission/"
    },
    "DISTRICTGEOJSONURL": "http://stg.eum.unicefuganda.org/static/app/data/districts.json",
    "DISTRICTJSONURL": "http://stg.eum.unicefuganda.org/static/app/data/district_name.json",
    "districtLayerStyle": {
        "weight": 1,
        "color": "#036E97",
        "fillColor": "#CCE9F4",
        "fillOpacity": 0.2,
        "opacity": 0.7
    },
    "selectedLayerStyle": {
        "weight": 1,
        "color": "@brand-primary",
        "fillOpacity": 0.8
    },
    "IPJSONURL": "http://stg.eum.unicefuganda.org/static/app/data/ip.json"
}
